ddmail_validators/__init__.py
ddmail_validators/validators.py
ddmail_validators-0.0.6.dist-info/METADATA
ddmail_validators-0.0.6.dist-info/WHEEL
ddmail_validators-0.0.6.dist-info/licenses/LICENSE
ddmail_validators-0.0.6.dist-info/RECORD
