Metadata-Version: 2.4
Name: ddmail_validators
Version: 0.0.6
Summary: Python package for validating input for the DDMail project
Project-URL: Homepage, https://github.com/drzobin/ddmail_validators
Project-URL: Issues, https://github.com/drzobin/ddmail_validators/issues
Author-email: Robin Larsson <me@drz.se>
License-Expression: AGPL-3.0
License-File: LICENSE
Classifier: Operating System :: OS Independent
Classifier: Programming Language :: Python :: 3
Requires-Python: >=3.8
Requires-Dist: dnspython
Provides-Extra: dev
Requires-Dist: dnspython; extra == 'dev'
Requires-Dist: hatchling; extra == 'dev'
Requires-Dist: pyright; extra == 'dev'
Requires-Dist: pytest; extra == 'dev'
Requires-Dist: pytest-cov; extra == 'dev'
Requires-Dist: ruff; extra == 'dev'
Requires-Dist: twine; extra == 'dev'
Provides-Extra: test
Requires-Dist: dnspython; extra == 'test'
Requires-Dist: flake8; extra == 'test'
Requires-Dist: pytest; extra == 'test'
Requires-Dist: pytest-cov; extra == 'test'
